{
	"Vue: import createApp": {
		"prefix": "import-createApp",
		"body": [
			"import { createApp$1 } from 'vue';"
		]
	},
	"Vue: import ref": {
		"prefix": "import-ref",
		"body": [
			"import { ref$1 } from 'vue';"
		]
	},
	"Vue: import watch": {
		"prefix": "import-watch",
		"body": [
			"import { watch$1 } from 'vue';"
		]
	},
	"Vue: import nextTick": {
		"prefix": "import-nextTick",
		"body": [
			"import { nextTick$1 } from 'vue';"
		]
	},
	"Vue: import defineComponent": {
		"prefix": "import-defineComponent",
		"body": [
			"import { defineComponent$1 } from 'vue';"
		]
	},
	"Vue: import defineAsyncComponent": {
		"prefix": "import-defineAsyncComponent",
		"body": [
			"import { defineAsyncComponent$1 } from 'vue';"
		]
	}
}
